{
  "db_name": "MySQL",
  "query": "SELECT * FROM phone_authorization WHERE phone = ?",
  "describe": {
    "columns": [
      {
        "ordinal": 0,
        "name": "id",
        "type_info": {
          "type": "Long",
          "flags": "NOT_NULL | PRIMARY_KEY | UNSIGNED | AUTO_INCREMENT",
          "char_set": 63,
          "max_size": 10
        }
      },
      {
        "ordinal": 1,
        "name": "phone",
        "type_info": {
          "type": "String",
          "flags": "NOT_NULL | UNIQUE_KEY | NO_DEFAULT_VALUE",
          "char_set": 224,
          "max_size": 52
        }
      },
      {
        "ordinal": 2,
        "name": "code",
        "type_info": {
          "type": "String",
          "flags": "NOT_NULL | NO_DEFAULT_VALUE",
          "char_set": 224,
          "max_size": 24
        }
      },
      {
        "ordinal": 3,
        "name": "created_at",
        "type_info": {
          "type": "Timestamp",
          "flags": "NOT_NULL | UNSIGNED | BINARY | TIMESTAMP",
          "char_set": 63,
          "max_size": 19
        }
      }
    ],
    "parameters": {
      "Right": 1
    },
    "nullable": [
      false,
      false,
      false,
      false
    ]
  },
  "hash": "4ae7455dcff677301e686dc36df281b63d75ad3b1dcd9aaae78173a84ce03475"
}
